{
  "adept": {
    "name": "Adept",
    "desc": "(Speed)% for the user to do two consecutive strikes.",
    "cost": 15,
    "emoji": "<:adept:1134253735535714335>",
    "reference": {
      "Character": "Zihark\nSoren"
    }
  },
  "aether": {
    "name": "Aether",
    "desc": "(Skill/2)% chance to do two strikes: One with a Sol effect, and the other ignores the enemy's defense.",
    "cost": 30,
    "emoji": "<:aether:1134253738379456582>",
    "reference": {
      "Class": "Vanguard"
    }
  },
  "astra": {
    "name": "Astra",
    "desc": "(Skill/2)% chance for the user to strike 5 times in a row. Each strike cannot crit and can miss.",
    "cost": 30,
    "emoji": "<:astra:1134253740015231099>",
    "reference": {
      "Class": "Trueblade"
    }
  },
  "aurora": {
    "name": "Aurora",
    "desc": "Deals half of the damage taken by the user back to the foe.",
    "cost": 0,
    "emoji": "<:aurora:1134253742691192883>",
    "reference": {
      "Class": "Enemy Only"
    }
  },
  "bane": {
    "name": "Bane",
    "desc": "(Skill/2)% chance to reduce foe's HP to 1.",
    "cost": 30,
    "emoji": "<:bane:1134253744020803604>",
    "reference": {
      "Class": "Whisper"
    }
  },
  "beastfoe": {
    "name": "Beastfoe",
    "desc": "All attacks do effective damage against beast laguz.",
    "cost": 15,
    "emoji": "<:beastfoe:1134253745723678862>",
    "reference": {}
  },
  "birdfoe": {
    "name": "Birdfoe",
    "desc": "All attacks do effective damage against bird laguz.",
    "cost": 15,
    "emoji": "<:birdfoe:1134253748789727302>",
    "reference": {}
  },
  "blessing": {
    "name": "Blessing",
    "desc": "Allies adjacent to the user restore HP (equal to user’s Magic) at the beginning of the turn.",
    "cost": 15,
    "emoji": "<:blessing:1134253750379360396>",
    "reference": {
      "Class": "Heron"
    }
  },
  "bloodtide": {
    "name": "Blood Tide",
    "desc": "Increases adjacent allies strength and skill by 5.",
    "cost": 10,
    "emoji": "<:bloodtide:1134253752984014858>",
    "reference": {
      "Class": "Red Dragon",
      "Character": "Ena\nGareth"
    }
  },
  "blossom": {
    "name": "Blossom",
    "desc": "User gains less experience (1/2 of the normal amount) and if a stat fails to increase, it rolls again for a second chance.",
    "cost": 20,
    "emoji": "<:blossom:1134253754485592237>",
    "reference": {}
  },
  "boon": {
    "name": "Boon",
    "desc": "Cures the status effects of all allies adjecent to the user at the start of the turn.",
    "cost": 15,
    "emoji": "<:boon:1134253755743879191>",
    "reference": {
      "Class": "Dragon Laguz",
      "Character": "Ena\nNasir"
    }
  },
  "cancel": {
    "name": "Cancel",
    "desc": "(Speed)% chance to block all damage done to the user.",
    "cost": 10,
    "emoji": "<:cancel:1134253762391855134>",
    "reference": {
      "Character": "Leonardo\nHaar"
    }
  },
  "canto": {
    "name": "Canto",
    "desc": "Allows the user to move again and use up any leftover movement distance.",
    "cost": 10,
    "emoji": "<:canto:1134253764921008319>",
    "reference": {
      "Class": "Mounted Units\nFlying Units"
    }
  },
  "celerity": {
    "name": "Celerity",
    "desc": "Grants +2 movement.",
    "cost": 15,
    "emoji": "<:celerity:1134253766359654442>",
    "reference": {
      "Character": "Tormod"
    }
  },
  "colossus": {
    "name": "Colossus",
    "desc": "(Skill/2)% chance to multiply user's strength by 3.",
    "cost": 25,
    "emoji": "<:colossus:1134253767768936448>",
    "reference": {
      "Class": "Reaver"
    }
  },
  "corona": {
    "name": "Corona",
    "desc": "(Skill/2)% chance to ignore foe's resistance and halves their hit rate for one turn.",
    "cost": 30,
    "emoji": "<:corona:1134253866783866931>",
    "reference": {
      "Class": "Light Priestess\nSaint\nChancellor"
    },
    "ALT_NAME": [
      "Covid19",
      "Covid"
    ]
  },
  "corrosion": {
    "name": "Corrosion",
    "desc": "(Skill/2)% chance to reduce enemy's weapon durability by (user's level).",
    "cost": 15,
    "emoji": "<:corrosion:1134253770927247370>",
    "reference": {
      "Class": "Beorc",
      "Character": "Bastian"
    }
  },
  "counter": {
    "name": "Counter",
    "desc": "(Skill)% chance to return half damage to the enemy when damaged.",
    "cost": 10,
    "emoji": "<:counter:1134253853974466571>",
    "reference": {
      "Character": "Titania"
    }
  },
  "crtplus10": {
    "name": "Critical +10",
    "desc": "Grants +10 crit.",
    "cost": 0,
    "emoji": "<:criticalplus10:1134253774358183956>",
    "reference": {
      "Class": "Swordmaster\nSniper\nSentinel"
    },
    "ALT_NAME": [
      "crit10",
      "crt10"
    ]
  },
  "crtplus15": {
    "name": "Critical +15",
    "desc": "Grants +15 crit.",
    "cost": 0,
    "emoji": "<:criticalplus15:1134253914678628422>",
    "reference": {
      "Class": "Marksman"
    },
    "ALT_NAME": [
      "crit15",
      "crt15"
    ]
  },
  "crtplus20": {
    "name": "Critical +20",
    "desc": "Grants +20 crit.",
    "cost": 0,
    "emoji": "<:criticalplus20:1134254257630085281>",
    "reference": {
      "Class": "Trueblade"
    },
    "ALT_NAME": [
      "crit20",
      "crt20"
    ]
  },
  "crtplus25": {
    "name": "Critical +25",
    "desc": "Grants +25 crit.",
    "cost": 0,
    "emoji": "<:criticalplus25:1134254294795825242>",
    "reference": {
      "Class": "Assassin"
    },
    "ALT_NAME": [
      "crit25",
      "crt25"
    ]
  },
  "crtplus5": {
    "name": "Critical +5",
    "desc": "Grants +5 crit.",
    "cost": 0,
    "emoji": "<:criticalplus5:1134253881132580974>",
    "reference": {
      "Class": "Myrmidon\nHalberdier\nReaver"
    },
    "ALT_NAME": [
      "crit5",
      "crt5"
    ]
  },
  "daunt": {
    "name": "Daunt",
    "desc": "Inflicts -5 accuracy/crit to enemies within 3 tiles.",
    "cost": 10,
    "emoji": "<:daunt:1134254296486133860>",
    "reference": {}
  },
  "deadeye": {
    "name": "Deadeye",
    "desc": "(Skill/2)% chance to multiply damage by 3 and inflict sleep on foe.",
    "cost": 25,
    "emoji": "<:deadeye:1134254297606017105>",
    "reference": {
      "Class": "Marksman"
    }
  },
  "disarm": {
    "name": "Disarm",
    "desc": "(Skill/2)% to unequip the foe's equipped weapon.",
    "cost": 10,
    "emoji": "<:disarm:1134254299346649148>",
    "reference": {
      "Class": "Beorc",
      "Character": "Brom"
    }
  },
  "discipline": {
    "name": "Discipline",
    "desc": "Doubles the user's weapon experience gain.",
    "cost": 10,
    "emoji": "<:discipline:1134254301364097125>",
    "reference": {
      "Class": "Beorc"
    }
  },
  "dragonfoe": {
    "name": "Dragonfoe",
    "desc": "All attacks do effective damage against dragon laguz.",
    "cost": 15,
    "emoji": "<:dragonfoe:1134254302706290729>",
    "reference": {}
  },
  "eclipse": {
    "name": "Eclipse",
    "desc": "(Skill/2)% chance to mutiply user's strength by 5 and ignore foe's defense.",
    "cost": 30,
    "emoji": "<:eclipse:1134254328941658254>",
    "reference": {
      "Class": "Black Knight"
    }
  },
  "flare": {
    "name": "Flare",
    "desc": "(Skill/2)% chance to ignore foe's resistance and restore HP based on damage dealt to the enemy.",
    "cost": 30,
    "emoji": "<:flare:1134254365436301365>",
    "reference": {
      "Class": "Archsage\nEmpress\nSummoner"
    }
  },
  "flourish": {
    "name": "Flourish",
    "desc": "Command: Reduces user's attack by half.",
    "cost": 10,
    "emoji": "<:flourish:1134254366715559956>",
    "reference": {}
  },
  "formshift": {
    "name": "Formshift",
    "desc": "User's transform gauge is always full.",
    "cost": 0,
    "emoji": "<:formshift:1134254369244708864>",
    "reference": {
      "Class": "Wolf Queen\nLion King\nRaven King\nHawk King\nDragon Prince"
    }
  },
  "fortune": {
    "name": "Fortune",
    "desc": "Negates the foe's ability to inflict critical hits against the user.",
    "cost": 20,
    "emoji": "<:fortune:1134254370293288970>",
    "reference": {
      "Character": "Meg\nCaineghis"
    }
  },
  "galdrar": {
    "name": "Galdrar",
    "desc": "Command: Effect changes depending on selected chant, new ones can be unlocked via level:\n**Lv.1 / Vigor:** Allows adjacent allies to move again.\n**Lv. 15 / Bliss:** Raises the biorhythm of adjacent allies to its highest point.\n**Lv. 15 / Sorrow:**: Lowers the biorhythm of adjacent enemies to its lowest point.\n**Lv. 30 / Valor:** Fills fully the transform gauge of adjacent laguz allies.\n**Lv. 40 / Recovery:** Restores the HP and cures the status conditions of nearby allies.\nLeanne's galdrar only affects units behind and in the front of her\nand Reyson while unstransformed only affects one adjacent unit.",
    "cost": 0,
    "emoji": "<:galdrar:1134254371039879301>",
    "reference": {
      "Class": "Heron"
    }
  },
  "gamble": {
    "name": "Gamble",
    "desc": "Command: User's accuracy is halved and the critical rate is doubled for one round of combat.",
    "cost": 10,
    "emoji": "<:gamble:1134254392921559141>",
    "reference": {
      "Character": "Kieran"
    }
  },
  "glare": {
    "name": "Glare",
    "desc": "Command: ([Skill/2] + [Biorhythm])% chance to inflict petrify on the target on hit.",
    "cost": 30,
    "emoji": "<:glare:1134254395475894332>",
    "reference": {
      "Character": "Nailah"
    }
  },
  "guard": {
    "name": "Guard",
    "desc": "If user has a support with an adjacent unit, and that ally is attacked, (??, based on suport level?)% chance for the user to take the hit instead.",
    "cost": 20,
    "emoji": "<:guard:1134254397170397305>",
    "reference": {
      "Character": "Sothe\nNailah"
    }
  },
  "howl": {
    "name": "Howl",
    "desc": "(Strength)% chance to inflict paralysis on foe if they initiate combat at 2 range and damages the user.",
    "cost": 20,
    "emoji": "<:howl:1134254399934447757>",
    "reference": {
      "Class": "Beast Laguz",
      "Character": "Volug"
    }
  },
  "imbue": {
    "name": "Imbue",
    "desc": "At the start of each turn, user restores HP as the same amount as user's magic. Can only be equipped by non-magic users (excl. White Dragon)",
    "cost": 15,
    "emoji": "<:imbue:1134254401616347136>",
    "reference": {
      "Character": "Fiona\nBlack Knight"
    }
  },
  "impale": {
    "name": "Impale",
    "desc": "(Skill/2)% chance to multiply damage by 4.",
    "cost": 30,
    "emoji": "<:impale:1134254403478634568>",
    "reference": {
      "Class": "Sentinel"
    }
  },
  "insight": {
    "name": "Insight",
    "desc": "Grants +20% accuracy and +5 fog vision.",
    "cost": 0,
    "emoji": "<:insight:1134254405126983781>",
    "reference": {
      "Character": "Janaff"
    }
  },
  "ire": {
    "name": "Ire",
    "desc": "(Skill/2)% chance to multiply damage by 3.",
    "cost": 30,
    "emoji": "<:ire:1134254431744045126>",
    "reference": {
      "Class": "Red Dragon\nWhite Dragon\nBlack Dragon"
    }
  },
  "lethality": {
    "name": "Lethality",
    "desc": "(Skill/2)% chance to kill the enemy. Cannot be used against bosses.",
    "cost": 30,
    "emoji": "<:lethality:1134254433958629406>",
    "reference": {
      "Class": "Assassin"
    }
  },
  "luna": {
    "name": "Luna",
    "desc": "(Skill/2)% chance to mutiply user's strength by 3 and ignore foe's defense.",
    "cost": 30,
    "emoji": "<:luna:1134254435128836331>",
    "reference": {
      "Class": "Marshall"
    }
  },
  "maelstrom": {
    "name": "Maelstrom",
    "desc": "(Skill)% chance to deal (user's strength) damage to foe if combat is happening above 1 range.",
    "cost": 20,
    "emoji": "<:maelstrom:1134254436554920026>",
    "reference": {
      "Class": "Hawk Laguz\nRaven Laguz",
      "Character": "Naesala"
    }
  },
  "mantle": {
    "name": "Mantle",
    "desc": "User can only be damaged by blessed weapons.",
    "cost": 0,
    "emoji": "<:mantle:1134254438597537923>",
    "reference": {
      "Character": "Lekain\nDheginsea\nLehran\nAshera"
    }
  },
  "mercy": {
    "name": "Mercy",
    "desc": "If user deals a death blow to foe, leave the enemy with 1 HP. If enemy is at 1 HP, they will dodge the attack. Can only be equipped by Elincia.",
    "cost": 10,
    "emoji": "<:mercy:1134254439998423041>",
    "reference": {
      "Character": "Elincia"
    }
  },
  "miracle": {
    "name": "Miracle",
    "desc": "(Luck)% chance to prevent an attack from killing the user. Instead the user's HP gets reduced to half of the current HP. If the current HP is 1 HP, the user will dodge.",
    "cost": 5,
    "emoji": "<:miracle:1134254442137530368>",
    "reference": {
      "Character": "Mist\nEna\nPelleas"
    }
  },
  "nighttide": {
    "name": "Night Tide",
    "desc": "Increases adjacent allies defense and resistance by 5.",
    "cost": 10,
    "emoji": "<:nighttide:1134254461783646228>",
    "reference": {
      "Class": "Black Dragon",
      "Character": "Kurthnaga"
    }
  },
  "nihil": {
    "name": "Nihil",
    "desc": "Negates enemy's combat skills.'",
    "cost": 20,
    "emoji": "<:nihil:1134254463754965023>",
    "reference": {
      "Character": "Nolan\nBlack Knight\nCalill\nIke (Vanguard)\nNasir"
    }
  },
  "nullify": {
    "name": "Nullify",
    "desc": "Negates foe's effective bonus towards the user.",
    "cost": 20,
    "emoji": "<:nullify:1134254465512374363>",
    "reference": {
      "Character": "Giffca"
    }
  },
  "paragon": {
    "name": "Paragon",
    "desc": "User gains double experience from combat.",
    "cost": 15,
    "emoji": "<:paragon:1134254466644852877>",
    "reference": {
      "Character": "Astrid\nGeoffrey"
    }
  },
  "parity": {
    "name": "Parity",
    "desc": "Command: Negates both user's and enemy's combat skills, terrain bonuses and support bonuses.",
    "cost": 10,
    "emoji": "<:parity:1134254469153042502>",
    "reference": {
      "Character": "Lucia"
    }
  },
  "pass": {
    "name": "Pass",
    "desc": "User can move through enemies.",
    "cost": 15,
    "emoji": "<:pass:1134254470482628658>",
    "reference": {
      "Character": "Heather"
    }
  },
  "pavise": {
    "name": "Pavise",
    "desc": "(Skill)% chance to ignore damage from one attack.",
    "cost": 20,
    "emoji": "<:pavise:1134254471791247612>",
    "reference": {
      "Character": "Tibarn"
    }
  },
  "provoke": {
    "name": "Provoke",
    "desc": "Makes user more likely to be attacked by the enemy.",
    "cost": 10,
    "emoji": "<:provoke:1134254496705421354>",
    "reference": {
      "Character": "Shinon\nSkrimir"
    }
  },
  "quickclaw": {
    "name": "Quickclaw",
    "desc": "(Speed)% chance to deal (user's strength) damage to foe if combat is happening above 1 range.",
    "cost": 20,
    "emoji": "<:quickclaw:1134254499062612191>",
    "reference": {
      "Class": "Beast Laguz",
      "Character": "Kyza"
    }
  },
  "rend": {
    "name": "Rend",
    "desc": "(Speed/2)% chance to multiply user's strength by 5 and inflict shock on the foe.",
    "cost": 30,
    "emoji": "<:rend:1134254500291547261>",
    "reference": {
      "Class": "Cat"
    }
  },
  "renewal": {
    "name": "Renewal",
    "desc": "At the beginning of each turn\nuser recovers HP equal to 1/10 of their max HP.",
    "cost": 15,
    "emoji": "<:renewal:1134254501885395044>",
    "reference": {
      "Character": "Elincia\nEna"
    }
  },
  "resolve": {
    "name": "Resolve",
    "desc": "When user is at half HP or lower, skill and speed are increased by 1.5.\n\n**JP**: Strength is also increased, user needs to be at 20% HP or lower, and has (Strength)% chance to activate.",
    "cost": 15,
    "emoji": "<:resolve:1134254503948988458>",
    "reference": {
      "Character": "Tauroneo\nSkrimir"
    }
  },
  "roar": {
    "name": "Roar",
    "desc": "(Strength/2)% chance to multiply user's strength by 3 and inflict shock on the foe.",
    "cost": 30,
    "emoji": "<:roar:1134254505110810715>",
    "reference": {
      "Class": "Tiger\nLion\nLion King"
    }
  },
  "sacrifice": {
    "name": "Sacrifice",
    "desc": "Command: Reduces own HP to recover an ally's HP and cures the status effect. Cannot be used at 1 HP.",
    "cost": 0,
    "emoji": "<:sacrifice:1134254506545266708>",
    "reference": {
      "Character": "Micaiah"
    }
  },
  "savage": {
    "name": "Savage",
    "desc": "(Strength/2)% chance to multiply user's strength by 3 and halve foe's skill by one turn.",
    "cost": 30,
    "emoji": "<:savage:1134254521657331764>",
    "reference": {
      "Class": "Wolf\nWolf Queen"
    }
  },
  "savior": {
    "name": "Savior",
    "desc": "User's stats aren't decreased when carrying an unit.",
    "cost": 10,
    "emoji": "<:savior:1134254611159588954>",
    "reference": {
      "Character": "Fiona\nTibarn"
    }
  },
  "shade": {
    "name": "Shade",
    "desc": "Makes user less likely to be attacked by the enemy.",
    "cost": 10,
    "emoji": "<:shade:1134254612950548491>",
    "reference": {
      "Class": "Beorc",
      "Character": "Ilyana"
    }
  },
  "shove": {
    "name": "Shove",
    "desc": "Push a ally 1 tile further if user's con + 2 > ally's weight.",
    "cost": 5,
    "emoji": "<:shove:1134254614745723054>",
    "reference": {
      "Class": "Walking Units"
    }
  },
  "shriek": {
    "name": "Shriek",
    "desc": "(Luck)% chance to reduce foe's luck to 0 for one turn if combat is happening above 1 range.",
    "cost": 20,
    "emoji": "<:shriek:1134254615983038504>",
    "reference": {
      "Class": "Raven Laguz\nHawk Laguz",
      "Character": "Vika"
    }
  },
  "smite": {
    "name": "Smite",
    "desc": "Command: Pushes units two tiles away if user's con + 2 > ally's weight.",
    "cost": 15,
    "emoji": "<:smite:1134254617295851541>",
    "reference": {
      "Character": "Mordecai"
    }
  },
  "sol": {
    "name": "Sol",
    "desc": "(Skill/2)% chance to multiply damage by 3 and restore HP based on damage dealt to the enemy.",
    "cost": 30,
    "emoji": "<:sol:1134254619434963015>",
    "reference": {
      "Class": "Silver Knight\nGold Knight\nValkyrie"
    }
  },
  "steal": {
    "name": "Steal",
    "desc": "Command: Steals an unequipped weapon/accessory or an item from the target's inventory if (user's speed > enemy's speed) and (user's strength > item's wt).",
    "cost": 0,
    "emoji": "<:steal:1134254635188756500>",
    "reference": {
      "Class": "Thief\nRogue\nWhisper"
    }
  },
  "stillness": {
    "name": "Stillness",
    "desc": "User is much less likely to be targeted by enemy units.",
    "cost": 25,
    "emoji": "<:stillness:1134254637575315547>",
    "reference": {
      "Class": "Beorc",
      "Character": "Volke"
    }
  },
  "stun": {
    "name": "Stun",
    "desc": "(Skill/2)% chance to multiply user's strength by 3 and inflict paralysis on the foe.",
    "cost": 25,
    "emoji": "<:stun:1134254639081074811>",
    "reference": {
      "Class": "Queen\nDragon Lord\nSeraph Knight"
    }
  },
  "tear": {
    "name": "Tear",
    "desc": "(Speed/2)% chance to mutiply user's strength by 3 for one turn and halve foe's speed for one turn.",
    "cost": 30,
    "emoji": "<:tear:1134254640540692500>",
    "reference": {
      "Class": "Raven\nRaven King\nHawk\nHawk King"
    }
  },
  "vantage": {
    "name": "Vantage",
    "desc": "(Speed)% chance for the user to strike first if foe initiates combat.",
    "cost": 10,
    "emoji": "<:vantage:1134254642352627762>",
    "reference": {
      "Character": "Mia\nNaesala"
    }
  },
  "vigilance": {
    "name": "Vigilance",
    "desc": "Grants +20 avoid and dodge.",
    "cost": 0,
    "emoji": "<:vigilance:1134254643321503785>",
    "reference": {
      "Character": "Ulki"
    }
  },
  "whitepool": {
    "name": "White Pool",
    "desc": "Increases adjacent allies magic and speed by 5.",
    "cost": 10,
    "emoji": "<:whitepool:1134254644604973116>",
    "reference": {
      "Class": "White Dragon",
      "Character": "Nasir"
    }
  },
  "wildheart": {
    "name": "Wildheart",
    "desc": "**Part 1:** User remains permanently shifted, but their transformation stat boosts are halved.\n**Part 2 onward:** User can shift and revert at will, but their transformation bonuses are halved. The transformation gauge still decreases, but open untransforming it is filled fully.",
    "cost": 10,
    "emoji": "<:wildheart:1134254654486761484>",
    "reference": {
      "Class": "Non-Heron Laguz",
      "Character": "Volug"
    }
  },
  "wrath": {
    "name": "Wrath",
    "desc": "+50 crit when user is at 30% HP or lower.\n\n**JP:** User needs to be at 20% HP or lower\nand has (Skill)% chance to activate.",
    "cost": 15,
    "emoji": "<:wrath:1134254656361611407>",
    "reference": {
      "Character": "Edward\nNealuchi\nNephenee"
    }
  }
}